hayloft/__init__.py
hayloft/app.py
hayloft/llama_index.py
hayloft/logger.py
hayloft/public/assets/index-883c7b1f.css
hayloft/public/assets/index-889253f9.js
hayloft/public/index.html
hayloft/schema.py
hayloft/sse.py
hayloft-0.4.1.dist-info/LICENSE
hayloft-0.4.1.dist-info/METADATA
hayloft-0.4.1.dist-info/WHEEL
hayloft-0.4.1.dist-info/entry_points.txt
hayloft-0.4.1.dist-info/RECORD
