Metadata-Version: 2.1
Name: hayloft
Version: 0.4.1
Summary: UI tool for LLM frameworks
Home-page: https://github.com/eturchenkov/hayloft
License: MIT
Keywords: UI tool,LLM app,tracking,monitoring,llama-index
Requires-Python: >=3.8,<4.0
Classifier: License :: OSI Approved :: MIT License
Classifier: Programming Language :: Python :: 3
Classifier: Programming Language :: Python :: 3.8
Classifier: Programming Language :: Python :: 3.9
Classifier: Programming Language :: Python :: 3.10
Classifier: Programming Language :: Python :: 3.11
Requires-Dist: bottle (>=0.12.25,<0.13.0)
Requires-Dist: bottle-cors-plugin (>=0.1.9,<0.2.0)
Requires-Dist: gevent (>=22.10.2,<23.0.0)
Requires-Dist: nanoid (>=2.0.0,<3.0.0)
Requires-Dist: peewee (>=3.16.2,<4.0.0)
Requires-Dist: requests (>=2.31.0,<3.0.0)
Project-URL: Repository, https://github.com/eturchenkov/hayloft
